easymql/__init__.py
easymql/actions.py
easymql/basics.py
easymql/core.py
easymql/exc.py
easymql/identifiers.py
easymql/keywords.py
easymql/meta.py
easymql/pipeline.py
easymql/proxies.py
easymql/utils.py
easymql/datatypes/__init__.py
easymql/datatypes/composite.py
easymql/datatypes/primary.py
easymql/expressions/__init__.py
easymql/expressions/accumulators.py
easymql/expressions/arithmetic.py
easymql/expressions/array.py
easymql/expressions/comparison.py
easymql/expressions/conditional.py
easymql/expressions/datasize.py
easymql/expressions/date.py
easymql/expressions/miscellaneous.py
easymql/expressions/object.py
easymql/expressions/others.py
easymql/expressions/set.py
easymql/expressions/strings.py
easymql/expressions/systemvariables.py
easymql/expressions/trigonometry.py
easymql/expressions/type.py
easymql/stages/__init__.py
easymql/stages/groupacc.py
easymql/stages/parts.py
easymql/stages/stages.py
easy_mql-1.0.1.dist-info/LICENSE
easy_mql-1.0.1.dist-info/METADATA
easy_mql-1.0.1.dist-info/WHEEL
easy_mql-1.0.1.dist-info/top_level.txt
easy_mql-1.0.1.dist-info/RECORD
